guts_base/__init__.py
guts_base/mod.py
guts_base/plot.py
guts_base/prob.py
guts_base/data/__init__.py
guts_base/data/expydb.py
guts_base/data/generator.py
guts_base/data/openguts.py
guts_base/data/preprocessing.py
guts_base/data/survival.py
guts_base/data/time_of_death.py
guts_base/data/utils.py
guts_base/sim/__init__.py
guts_base/sim/base.py
guts_base/sim/constructors.py
guts_base/sim/ecx.py
guts_base/sim/mempy.py
guts_base/sim/report.py
guts_base/sim/utils.py
guts_base-1.0.9.dist-info/licenses/LICENSE
guts_base-1.0.9.dist-info/METADATA
guts_base-1.0.9.dist-info/WHEEL
guts_base-1.0.9.dist-info/entry_points.txt
guts_base-1.0.9.dist-info/top_level.txt
guts_base-1.0.9.dist-info/RECORD
