Metadata-Version: 2.4
Name: guts_base
Version: 1.0.9
Summary: Basic GUTS model implementation in pymob
Author-email: Florian Schunck <fluncki@protonmail.com>
License:                     GNU GENERAL PUBLIC LICENSE
Project-URL: Homepage, https://gitlab.uni-osnabrueck.de/fschunck/guts-base
Project-URL: Issue Tracker, https://gitlab.uni-osnabrueck.de/fschunck/guts-base/issues
Classifier: Development Status :: 4 - Beta
Classifier: Programming Language :: Python :: 3
Classifier: Natural Language :: English
Classifier: License :: OSI Approved :: GNU General Public License v3 (GPLv3)
Classifier: Operating System :: OS Independent
Classifier: Topic :: Scientific/Engineering :: Bio-Informatics
Requires-Python: <3.12,>=3.10
License-File: LICENSE
Requires-Dist: openpyxl>=3.1.3
Requires-Dist: Bottleneck>=1.5.0
Requires-Dist: expydb>=0.6.0
Requires-Dist: pymob[interactive,numpyro]<0.6.0,>=0.5.10
Requires-Dist: pint
Provides-Extra: dev
Requires-Dist: pytest>=7.3; extra == "dev"
Requires-Dist: bumpver; extra == "dev"
Requires-Dist: pre-commit; extra == "dev"
Requires-Dist: ipykernel; extra == "dev"
Requires-Dist: ipywidgets; extra == "dev"
Dynamic: license-file
